{
  "Type": "DataTable",
  "Name": "GuideTask",
  "Class": "UScriptClass'DataTable'",
  "Flags": "RF_Public | RF_Standalone | RF_Transactional | RF_WasLoaded | RF_LoadCompleted",
  "Properties": {
    "RowStruct": {
      "ObjectName": "ScriptStruct'CyGuideTaskTableRow'",
      "ObjectPath": "/Script/PMGame"
    }
  },
  "Rows": {
    "60001": {
      "Id": 60001,
      "NextTaskId": 60002,
      "Title": {
        "Namespace": "GuideTask",
        "Key": "60001_Title",
        "SourceString": "入门",
        "LocalizedString": "入门"
      },
      "Desc": {
        "Namespace": "GuideTask",
        "Key": "60001_Desc",
        "SourceString": "完成1场任意模式",
        "LocalizedString": "完成1场任意模式"
      },
      "Type": 6,
      "UniqueType": 0,
      "Prize": [
        {
          "ItemId": 40006,
          "ItemAmount": 5
        }
      ],
      "TaskConditions": [
        {
          "MainCondition": {
            "MainType": "ECyTaskMainConditionType::Lobby",
            "GameCondition": "ECyTaskGameConditionType::None",
            "GameResult": "ECyGameResultType::None",
            "RoundResult": "ECyRoundResultType::None",
            "bFriendTeam": false,
            "bNoFriendTeam": false,
            "BattleCondition": "ECyTaskBattleConditionType::None",
            "bHeadshot": false,
            "bHitBody": false,
            "bFirstKill": false,
            "bRevenge": false,
            "MultiKillLimit": 0,
            "HitDistLimit": 0,
            "bBlind": false,
            "ActionCondition": "ECyTaskActionConditionType::None",
            "RoleIds": [],
            "RoleProfessions": [],
            "RoleTeams": [],
            "MeshModes": [],
            "EnemyMeshModes": [],
            "WeaponTypes": [],
            "WeaponHoldType": [],
            "SkillTypes": [],
            "Num": 1,
            "EventInstigatorTeamRole": "ECyTaskTeamRoleType::None",
            "EventTargetTeamRole": "ECyTaskTeamRoleType::None",
            "BehaviorId": 64,
            "RandomCondition": [],
            "EscortActionType": [],
            "ZombieActionType": [],
            "WeaponIds": []
          },
          "LimitConditions": []
        }
      ],
      "TaskLimit": {
        "GameTypes": [],
        "ModeTypes": []
      },
      "Lev": 2,
      "GuideName": "CartGuide",
      "RewardShow": 1
    },
    "60002": {
      "Id": 60002,
      "NextTaskId": 60003,
      "Title": {
        "Namespace": "GuideTask",
        "Key": "60002_Title",
        "SourceString": "技能",
        "LocalizedString": "技能"
      },
      "Desc": {
        "Namespace": "GuideTask",
        "Key": "60002_Desc",
        "SourceString": "使用Q技能5次",
        "LocalizedString": "使用Q技能5次"
      },
      "Type": 6,
      "UniqueType": 0,
      "Prize": [
        {
          "ItemId": 20128058,
          "ItemAmount": 1
        }
      ],
      "TaskConditions": [
        {
          "MainCondition": {
            "MainType": "ECyTaskMainConditionType::Battle",
            "GameCondition": "ECyTaskGameConditionType::None",
            "GameResult": "ECyGameResultType::None",
            "RoundResult": "ECyRoundResultType::None",
            "bFriendTeam": false,
            "bNoFriendTeam": false,
            "BattleCondition": "ECyTaskBattleConditionType::UseSkillNum",
            "bHeadshot": false,
            "bHitBody": false,
            "bFirstKill": false,
            "bRevenge": false,
            "MultiKillLimit": 0,
            "HitDistLimit": 0,
            "bBlind": false,
            "ActionCondition": "ECyTaskActionConditionType::None",
            "RoleIds": [],
            "RoleProfessions": [],
            "RoleTeams": [],
            "MeshModes": [],
            "EnemyMeshModes": [],
            "WeaponTypes": [],
            "WeaponHoldType": [],
            "SkillTypes": [
              "ECyPlayerSkillType::Q"
            ],
            "Num": 5,
            "EventInstigatorTeamRole": "ECyTaskTeamRoleType::None",
            "EventTargetTeamRole": "ECyTaskTeamRoleType::None",
            "BehaviorId": 0,
            "RandomCondition": [],
            "EscortActionType": [],
            "ZombieActionType": [],
            "WeaponIds": []
          },
          "LimitConditions": []
        }
      ],
      "TaskLimit": {
        "GameTypes": [],
        "ModeTypes": []
      },
      "Lev": 4,
      "GuideName": "",
      "RewardShow": 0
    },
    "60003": {
      "Id": 60003,
      "NextTaskId": 60004,
      "Title": {
        "Namespace": "GuideTask",
        "Key": "60003_Title",
        "SourceString": "射击",
        "LocalizedString": "射击"
      },
      "Desc": {
        "Namespace": "GuideTask",
        "Key": "60003_Desc",
        "SourceString": "击杀或助攻5名敌人",
        "LocalizedString": "击杀或助攻5名敌人"
      },
      "Type": 6,
      "UniqueType": 0,
      "Prize": [
        {
          "ItemId": 40006,
          "ItemAmount": 5
        }
      ],
      "TaskConditions": [
        {
          "MainCondition": {
            "MainType": "ECyTaskMainConditionType::Battle",
            "GameCondition": "ECyTaskGameConditionType::None",
            "GameResult": "ECyGameResultType::None",
            "RoundResult": "ECyRoundResultType::None",
            "bFriendTeam": false,
            "bNoFriendTeam": false,
            "BattleCondition": "ECyTaskBattleConditionType::ParticipateKillNum",
            "bHeadshot": false,
            "bHitBody": false,
            "bFirstKill": false,
            "bRevenge": false,
            "MultiKillLimit": 0,
            "HitDistLimit": 0,
            "bBlind": false,
            "ActionCondition": "ECyTaskActionConditionType::None",
            "RoleIds": [],
            "RoleProfessions": [],
            "RoleTeams": [],
            "MeshModes": [],
            "EnemyMeshModes": [],
            "WeaponTypes": [],
            "WeaponHoldType": [],
            "SkillTypes": [],
            "Num": 5,
            "EventInstigatorTeamRole": "ECyTaskTeamRoleType::None",
            "EventTargetTeamRole": "ECyTaskTeamRoleType::None",
            "BehaviorId": 0,
            "RandomCondition": [],
            "EscortActionType": [],
            "ZombieActionType": [],
            "WeaponIds": []
          },
          "LimitConditions": []
        }
      ],
      "TaskLimit": {
        "GameTypes": [],
        "ModeTypes": []
      },
      "Lev": 4,
      "GuideName": "PushCar",
      "RewardShow": 0
    },
    "60004": {
      "Id": 60004,
      "NextTaskId": 0,
      "Title": {
        "Namespace": "GuideTask",
        "Key": "60004_Title",
        "SourceString": "胜利",
        "LocalizedString": "胜利"
      },
      "Desc": {
        "Namespace": "GuideTask",
        "Key": "60004_Desc",
        "SourceString": "取得1场任意模式胜利",
        "LocalizedString": "取得1场任意模式胜利"
      },
      "Type": 6,
      "UniqueType": 0,
      "Prize": [
        {
          "ItemId": 137,
          "ItemAmount": 1
        }
      ],
      "TaskConditions": [
        {
          "MainCondition": {
            "MainType": "ECyTaskMainConditionType::Lobby",
            "GameCondition": "ECyTaskGameConditionType::None",
            "GameResult": "ECyGameResultType::None",
            "RoundResult": "ECyRoundResultType::None",
            "bFriendTeam": false,
            "bNoFriendTeam": false,
            "BattleCondition": "ECyTaskBattleConditionType::None",
            "bHeadshot": false,
            "bHitBody": false,
            "bFirstKill": false,
            "bRevenge": false,
            "MultiKillLimit": 0,
            "HitDistLimit": 0,
            "bBlind": false,
            "ActionCondition": "ECyTaskActionConditionType::None",
            "RoleIds": [],
            "RoleProfessions": [],
            "RoleTeams": [],
            "MeshModes": [],
            "EnemyMeshModes": [],
            "WeaponTypes": [],
            "WeaponHoldType": [],
            "SkillTypes": [],
            "Num": 1,
            "EventInstigatorTeamRole": "ECyTaskTeamRoleType::None",
            "EventTargetTeamRole": "ECyTaskTeamRoleType::None",
            "BehaviorId": 56,
            "RandomCondition": [],
            "EscortActionType": [],
            "ZombieActionType": [],
            "WeaponIds": []
          },
          "LimitConditions": []
        }
      ],
      "TaskLimit": {
        "GameTypes": [],
        "ModeTypes": []
      },
      "Lev": 4,
      "GuideName": "PushCar",
      "RewardShow": 0
    }
  }
}