{
  "Type": "DataTable",
  "Name": "RoleFavorabilityEvent",
  "Class": "UScriptClass'DataTable'",
  "Properties": {
    "RowStruct": {
      "ObjectName": "ScriptStruct'CyRoleFavorabilityEventTableRow'",
      "ObjectPath": "/Script/PMGame"
    }
  },
  "Rows": {
    "14601": {
      "Id": 14601,
      "RoleId": 146,
      "FavoLevel": 1,
      "FavoPrize": [
        {
          "ItemId": 33002003,
          "ItemAmount": 1
        }
      ],
      "FavoPrizeDescription": {
        "CultureInvariantString": null
      },
      "FavoPrizeName": {
        "CultureInvariantString": null
      },
      "EmoticonsPicture": {
        "AssetPathName": "None",
        "SubPathString": ""
      },
      "StoryType": 1,
      "SmsId": 14601001,
      "PartUnlock": [
        1
      ],
      "AreaUnlock": [
        1,
        7
      ],
      "RoleprofileUnlock": 0,
      "BiographyUnlock": [
        14601
      ],
      "UnlockPledgeItem": 0,
      "PledgeAvgId": 0,
      "PledgeSeqId": 0
    },
    "14602": {
      "Id": 14602,
      "RoleId": 146,
      "FavoLevel": 2,
      "FavoPrize": [
        {
          "ItemId": 30000030,
          "ItemAmount": 1
        }
      ],
      "FavoPrizeDescription": {
        "CultureInvariantString": null
      },
      "FavoPrizeName": {
        "CultureInvariantString": null
      },
      "EmoticonsPicture": {
        "AssetPathName": "None",
        "SubPathString": ""
      },
      "StoryType": 1,
      "SmsId": 14602001,
      "PartUnlock": [
        0
      ],
      "AreaUnlock": [
        0
      ],
      "RoleprofileUnlock": 146,
      "BiographyUnlock": [
        14602,
        14603
      ],
      "UnlockPledgeItem": 14601,
      "PledgeAvgId": 146201000,
      "PledgeSeqId": 0
    },
    "14603": {
      "Id": 14603,
      "RoleId": 146,
      "FavoLevel": 3,
      "FavoPrize": [
        {
          "ItemId": 60000036,
          "ItemAmount": 1
        },
        {
          "ItemId": 60000037,
          "ItemAmount": 1
        }
      ],
      "FavoPrizeDescription": {
        "Namespace": "RoleFavorabilityEvent",
        "Key": "10103_FavoPrizeDescription",
        "SourceString": "【表情包详细描述点击预览查看】",
        "LocalizedString": "【表情包详细描述点击预览查看】"
      },
      "FavoPrizeName": {
        "Namespace": "RoleFavorabilityEvent",
        "Key": "14603_FavoPrizeName",
        "SourceString": "星绘表情x2:\"担心\"||\"好奇\"",
        "LocalizedString": "星绘表情x2:\"担心\"||\"好奇\""
      },
      "EmoticonsPicture": {
        "AssetPathName": "/Game/PaperMan/UI/Atlas/DynamicResource/Emote/ApartmentEmotePack/T_Dynamic_Emote_61146002.T_Dynamic_Emote_61146002",
        "SubPathString": ""
      },
      "StoryType": 1,
      "SmsId": 14603001,
      "PartUnlock": [
        3
      ],
      "AreaUnlock": [
        0
      ],
      "RoleprofileUnlock": 0,
      "BiographyUnlock": [
        14604,
        14605
      ],
      "UnlockPledgeItem": 0,
      "PledgeAvgId": 0,
      "PledgeSeqId": 0
    },
    "14604": {
      "Id": 14604,
      "RoleId": 146,
      "FavoLevel": 4,
      "FavoPrize": [
        {
          "ItemId": 31000080,
          "ItemAmount": 1
        }
      ],
      "FavoPrizeDescription": {
        "CultureInvariantString": null
      },
      "FavoPrizeName": {
        "CultureInvariantString": null
      },
      "EmoticonsPicture": {
        "AssetPathName": "None",
        "SubPathString": ""
      },
      "StoryType": 1,
      "SmsId": 14604001,
      "PartUnlock": [
        0
      ],
      "AreaUnlock": [
        0
      ],
      "RoleprofileUnlock": 0,
      "BiographyUnlock": [
        0
      ],
      "UnlockPledgeItem": 14602,
      "PledgeAvgId": 146202000,
      "PledgeSeqId": 0
    },
    "14605": {
      "Id": 14605,
      "RoleId": 146,
      "FavoLevel": 5,
      "FavoPrize": [
        {
          "ItemId": 40001,
          "ItemAmount": 1
        }
      ],
      "FavoPrizeDescription": {
        "CultureInvariantString": null
      },
      "FavoPrizeName": {
        "CultureInvariantString": null
      },
      "EmoticonsPicture": {
        "AssetPathName": "None",
        "SubPathString": ""
      },
      "StoryType": 1,
      "SmsId": 14605001,
      "PartUnlock": [
        0
      ],
      "AreaUnlock": [
        2
      ],
      "RoleprofileUnlock": 0,
      "BiographyUnlock": [
        0
      ],
      "UnlockPledgeItem": 0,
      "PledgeAvgId": 0,
      "PledgeSeqId": 0
    },
    "14606": {
      "Id": 14606,
      "RoleId": 146,
      "FavoLevel": 6,
      "FavoPrize": [
        {
          "ItemId": 60000038,
          "ItemAmount": 1
        },
        {
          "ItemId": 60000039,
          "ItemAmount": 1
        },
        {
          "ItemId": 60000040,
          "ItemAmount": 1
        }
      ],
      "FavoPrizeDescription": {
        "Namespace": "RoleFavorabilityEvent",
        "Key": "10103_FavoPrizeDescription",
        "SourceString": "【表情包详细描述点击预览查看】",
        "LocalizedString": "【表情包详细描述点击预览查看】"
      },
      "FavoPrizeName": {
        "Namespace": "RoleFavorabilityEvent",
        "Key": "14606_FavoPrizeName",
        "SourceString": "星绘表情x3:\"喜欢\"||\"送你星星\"||\"问候\"",
        "LocalizedString": "星绘表情x3:\"喜欢\"||\"送你星星\"||\"问候\""
      },
      "EmoticonsPicture": {
        "AssetPathName": "/Game/PaperMan/UI/Atlas/DynamicResource/Emote/ApartmentEmotePack/T_Dynamic_Emote_61146003.T_Dynamic_Emote_61146003",
        "SubPathString": ""
      },
      "StoryType": 1,
      "SmsId": 14606001,
      "PartUnlock": [
        0
      ],
      "AreaUnlock": [
        0
      ],
      "RoleprofileUnlock": 0,
      "BiographyUnlock": [
        0
      ],
      "UnlockPledgeItem": 14603,
      "PledgeAvgId": 146203000,
      "PledgeSeqId": 0
    },
    "14607": {
      "Id": 14607,
      "RoleId": 146,
      "FavoLevel": 7,
      "FavoPrize": [
        {
          "ItemId": 6,
          "ItemAmount": 200
        }
      ],
      "FavoPrizeDescription": {
        "CultureInvariantString": null
      },
      "FavoPrizeName": {
        "CultureInvariantString": null
      },
      "EmoticonsPicture": {
        "AssetPathName": "None",
        "SubPathString": ""
      },
      "StoryType": 1,
      "SmsId": 14607001,
      "PartUnlock": [
        2
      ],
      "AreaUnlock": [
        0
      ],
      "RoleprofileUnlock": 0,
      "BiographyUnlock": [
        0
      ],
      "UnlockPledgeItem": 0,
      "PledgeAvgId": 0,
      "PledgeSeqId": 0
    },
    "14608": {
      "Id": 14608,
      "RoleId": 146,
      "FavoLevel": 8,
      "FavoPrize": [
        {
          "ItemId": 20146055,
          "ItemAmount": 1
        }
      ],
      "FavoPrizeDescription": {
        "CultureInvariantString": null
      },
      "FavoPrizeName": {
        "CultureInvariantString": null
      },
      "EmoticonsPicture": {
        "AssetPathName": "None",
        "SubPathString": ""
      },
      "StoryType": 1,
      "SmsId": 14608001,
      "PartUnlock": [
        0
      ],
      "AreaUnlock": [
        5
      ],
      "RoleprofileUnlock": 0,
      "BiographyUnlock": [
        0
      ],
      "UnlockPledgeItem": 14604,
      "PledgeAvgId": 146204000,
      "PledgeSeqId": 0
    },
    "14609": {
      "Id": 14609,
      "RoleId": 146,
      "FavoLevel": 9,
      "FavoPrize": [
        {
          "ItemId": 30000031,
          "ItemAmount": 1
        }
      ],
      "FavoPrizeDescription": {
        "CultureInvariantString": null
      },
      "FavoPrizeName": {
        "CultureInvariantString": null
      },
      "EmoticonsPicture": {
        "AssetPathName": "None",
        "SubPathString": ""
      },
      "StoryType": 1,
      "SmsId": 14609001,
      "PartUnlock": [
        0
      ],
      "AreaUnlock": [
        0
      ],
      "RoleprofileUnlock": 0,
      "BiographyUnlock": [
        0
      ],
      "UnlockPledgeItem": 0,
      "PledgeAvgId": 0,
      "PledgeSeqId": 0
    },
    "14610": {
      "Id": 14610,
      "RoleId": 146,
      "FavoLevel": 10,
      "FavoPrize": [
        {
          "ItemId": 40001,
          "ItemAmount": 2
        }
      ],
      "FavoPrizeDescription": {
        "CultureInvariantString": null
      },
      "FavoPrizeName": {
        "CultureInvariantString": null
      },
      "EmoticonsPicture": {
        "AssetPathName": "None",
        "SubPathString": ""
      },
      "StoryType": 1,
      "SmsId": 14610001,
      "PartUnlock": [
        0
      ],
      "AreaUnlock": [
        0
      ],
      "RoleprofileUnlock": 0,
      "BiographyUnlock": [
        0
      ],
      "UnlockPledgeItem": 0,
      "PledgeAvgId": 0,
      "PledgeSeqId": 0
    },
    "10101": {
      "Id": 10101,
      "RoleId": 101,
      "FavoLevel": 1,
      "FavoPrize": [
        {
          "ItemId": 33002001,
          "ItemAmount": 1
        }
      ],
      "FavoPrizeDescription": {
        "CultureInvariantString": null
      },
      "FavoPrizeName": {
        "CultureInvariantString": null
      },
      "EmoticonsPicture": {
        "AssetPathName": "None",
        "SubPathString": ""
      },
      "StoryType": 1,
      "SmsId": 10101001,
      "PartUnlock": [
        1
      ],
      "AreaUnlock": [
        4,
        7
      ],
      "RoleprofileUnlock": 101,
      "BiographyUnlock": [
        10101
      ],
      "UnlockPledgeItem": 0,
      "PledgeAvgId": 0,
      "PledgeSeqId": 0
    },
    "10102": {
      "Id": 10102,
      "RoleId": 101,
      "FavoLevel": 2,
      "FavoPrize": [
        {
          "ItemId": 30000016,
          "ItemAmount": 1
        }
      ],
      "FavoPrizeDescription": {
        "CultureInvariantString": null
      },
      "FavoPrizeName": {
        "CultureInvariantString": null
      },
      "EmoticonsPicture": {
        "AssetPathName": "None",
        "SubPathString": ""
      },
      "StoryType": 1,
      "SmsId": 10102001,
      "PartUnlock": [
        0
      ],
      "AreaUnlock": [
        0
      ],
      "RoleprofileUnlock": 0,
      "BiographyUnlock": [
        10102,
        10103
      ],
      "UnlockPledgeItem": 10101,
      "PledgeAvgId": 101201000,
      "PledgeSeqId": 0
    },
    "10103": {
      "Id": 10103,
      "RoleId": 101,
      "FavoLevel": 3,
      "FavoPrize": [
        {
          "ItemId": 60000031,
          "ItemAmount": 1
        },
        {
          "ItemId": 60000032,
          "ItemAmount": 1
        }
      ],
      "FavoPrizeDescription": {
        "Namespace": "RoleFavorabilityEvent",
        "Key": "10103_FavoPrizeDescription",
        "SourceString": "【表情包详细描述点击预览查看】",
        "LocalizedString": "【表情包详细描述点击预览查看】"
      },
      "FavoPrizeName": {
        "Namespace": "RoleFavorabilityEvent",
        "Key": "10103_FavoPrizeName",
        "SourceString": "米雪儿表情x2:\"得意\"||\"期待\"",
        "LocalizedString": "米雪儿表情x2:\"得意\"||\"期待\""
      },
      "EmoticonsPicture": {
        "AssetPathName": "/Game/PaperMan/UI/Atlas/DynamicResource/Emote/ApartmentEmotePack/T_Dynamic_Emote_61101002.T_Dynamic_Emote_61101002",
        "SubPathString": ""
      },
      "StoryType": 1,
      "SmsId": 10103001,
      "PartUnlock": [
        3
      ],
      "AreaUnlock": [
        0
      ],
      "RoleprofileUnlock": 0,
      "BiographyUnlock": [
        10104,
        10105
      ],
      "UnlockPledgeItem": 0,
      "PledgeAvgId": 0,
      "PledgeSeqId": 0
    },
    "10104": {
      "Id": 10104,
      "RoleId": 101,
      "FavoLevel": 4,
      "FavoPrize": [
        {
          "ItemId": 31000081,
          "ItemAmount": 1
        }
      ],
      "FavoPrizeDescription": {
        "CultureInvariantString": null
      },
      "FavoPrizeName": {
        "CultureInvariantString": null
      },
      "EmoticonsPicture": {
        "AssetPathName": "None",
        "SubPathString": ""
      },
      "StoryType": 1,
      "SmsId": 10104001,
      "PartUnlock": [
        0
      ],
      "AreaUnlock": [
        0
      ],
      "RoleprofileUnlock": 0,
      "BiographyUnlock": [
        0
      ],
      "UnlockPledgeItem": 10102,
      "PledgeAvgId": 101202000,
      "PledgeSeqId": 0
    },
    "10105": {
      "Id": 10105,
      "RoleId": 101,
      "FavoLevel": 5,
      "FavoPrize": [
        {
          "ItemId": 40001,
          "ItemAmount": 1
        }
      ],
      "FavoPrizeDescription": {
        "CultureInvariantString": null
      },
      "FavoPrizeName": {
        "CultureInvariantString": null
      },
      "EmoticonsPicture": {
        "AssetPathName": "None",
        "SubPathString": ""
      },
      "StoryType": 2,
      "SmsId": 10105001,
      "PartUnlock": [
        0
      ],
      "AreaUnlock": [
        2
      ],
      "RoleprofileUnlock": 0,
      "BiographyUnlock": [
        0
      ],
      "UnlockPledgeItem": 0,
      "PledgeAvgId": 0,
      "PledgeSeqId": 0
    },
    "10106": {
      "Id": 10106,
      "RoleId": 101,
      "FavoLevel": 6,
      "FavoPrize": [
        {
          "ItemId": 60000033,
          "ItemAmount": 1
        },
        {
          "ItemId": 60000034,
          "ItemAmount": 1
        },
        {
          "ItemId": 60000035,
          "ItemAmount": 1
        }
      ],
      "FavoPrizeDescription": {
        "Namespace": "RoleFavorabilityEvent",
        "Key": "10103_FavoPrizeDescription",
        "SourceString": "【表情包详细描述点击预览查看】",
        "LocalizedString": "【表情包详细描述点击预览查看】"
      },
      "FavoPrizeName": {
        "Namespace": "RoleFavorabilityEvent",
        "Key": "10106_FavoPrizeName",
        "SourceString": "米雪儿表情x3:\"思考\"||\"委屈\"||\"问候\"",
        "LocalizedString": "米雪儿表情x3:\"思考\"||\"委屈\"||\"问候\""
      },
      "EmoticonsPicture": {
        "AssetPathName": "/Game/PaperMan/UI/Atlas/DynamicResource/Emote/ApartmentEmotePack/T_Dynamic_Emote_61101003.T_Dynamic_Emote_61101003",
        "SubPathString": ""
      },
      "StoryType": 1,
      "SmsId": 10106001,
      "PartUnlock": [
        0
      ],
      "AreaUnlock": [
        0
      ],
      "RoleprofileUnlock": 0,
      "BiographyUnlock": [
        0
      ],
      "UnlockPledgeItem": 10103,
      "PledgeAvgId": 101203000,
      "PledgeSeqId": 0
    },
    "10107": {
      "Id": 10107,
      "RoleId": 101,
      "FavoLevel": 7,
      "FavoPrize": [
        {
          "ItemId": 6,
          "ItemAmount": 200
        }
      ],
      "FavoPrizeDescription": {
        "CultureInvariantString": null
      },
      "FavoPrizeName": {
        "CultureInvariantString": null
      },
      "EmoticonsPicture": {
        "AssetPathName": "None",
        "SubPathString": ""
      },
      "StoryType": 1,
      "SmsId": 10107001,
      "PartUnlock": [
        2
      ],
      "AreaUnlock": [
        0
      ],
      "RoleprofileUnlock": 0,
      "BiographyUnlock": [
        0
      ],
      "UnlockPledgeItem": 0,
      "PledgeAvgId": 0,
      "PledgeSeqId": 0
    },
    "10108": {
      "Id": 10108,
      "RoleId": 101,
      "FavoLevel": 8,
      "FavoPrize": [
        {
          "ItemId": 20101054,
          "ItemAmount": 1
        }
      ],
      "FavoPrizeDescription": {
        "CultureInvariantString": null
      },
      "FavoPrizeName": {
        "CultureInvariantString": null
      },
      "EmoticonsPicture": {
        "AssetPathName": "None",
        "SubPathString": ""
      },
      "StoryType": 1,
      "SmsId": 10108001,
      "PartUnlock": [
        0
      ],
      "AreaUnlock": [
        0
      ],
      "RoleprofileUnlock": 0,
      "BiographyUnlock": [
        0
      ],
      "UnlockPledgeItem": 10104,
      "PledgeAvgId": 101204000,
      "PledgeSeqId": 0
    },
    "10109": {
      "Id": 10109,
      "RoleId": 101,
      "FavoLevel": 9,
      "FavoPrize": [
        {
          "ItemId": 30000037,
          "ItemAmount": 1
        }
      ],
      "FavoPrizeDescription": {
        "CultureInvariantString": null
      },
      "FavoPrizeName": {
        "CultureInvariantString": null
      },
      "EmoticonsPicture": {
        "AssetPathName": "None",
        "SubPathString": ""
      },
      "StoryType": 1,
      "SmsId": 10109001,
      "PartUnlock": [
        0
      ],
      "AreaUnlock": [
        0
      ],
      "RoleprofileUnlock": 0,
      "BiographyUnlock": [
        0
      ],
      "UnlockPledgeItem": 0,
      "PledgeAvgId": 0,
      "PledgeSeqId": 0
    },
    "10110": {
      "Id": 10110,
      "RoleId": 101,
      "FavoLevel": 10,
      "FavoPrize": [
        {
          "ItemId": 40001,
          "ItemAmount": 2
        }
      ],
      "FavoPrizeDescription": {
        "CultureInvariantString": null
      },
      "FavoPrizeName": {
        "CultureInvariantString": null
      },
      "EmoticonsPicture": {
        "AssetPathName": "None",
        "SubPathString": ""
      },
      "StoryType": 2,
      "SmsId": 10110001,
      "PartUnlock": [
        0
      ],
      "AreaUnlock": [
        0
      ],
      "RoleprofileUnlock": 0,
      "BiographyUnlock": [
        0
      ],
      "UnlockPledgeItem": 0,
      "PledgeAvgId": 0,
      "PledgeSeqId": 0
    }
  }
}