{
  "Type": "DataTable",
  "Name": "GuideStep",
  "Class": "UScriptClass'DataTable'",
  "Flags": "RF_Public | RF_Standalone | RF_Transactional | RF_WasLoaded | RF_LoadCompleted",
  "Properties": {
    "RowStruct": {
      "ObjectName": "ScriptStruct'CyGuideStepTableRow'",
      "ObjectPath": "/Script/PMGame"
    }
  },
  "Rows": {
    "1000001": {
      "TaskSubid": 1000001,
      "TaskParentid": 10000,
      "TaskType": 1,
      "ParamType": 0,
      "TaskParam": 0,
      "PageClass": "NavigationPage",
      "ParentClass": {
        "AssetPathName": "None",
        "SubPathString": ""
      },
      "TargetName": "",
      "MaskShape": 0,
      "MaskZoom": 0,
      "MaskType": 1,
      "DialogId": 1000001
    },
    "1000002": {
      "TaskSubid": 1000002,
      "TaskParentid": 10000,
      "TaskType": 1,
      "ParamType": 0,
      "TaskParam": 0,
      "PageClass": "NavigationPage",
      "ParentClass": {
        "AssetPathName": "None",
        "SubPathString": ""
      },
      "TargetName": "",
      "MaskShape": 0,
      "MaskZoom": 0,
      "MaskType": 1,
      "DialogId": 1000002
    },
    "1000003": {
      "TaskSubid": 1000003,
      "TaskParentid": 10000,
      "TaskType": 3,
      "ParamType": 1,
      "TaskParam": 2,
      "PageClass": "NavigationPage",
      "ParentClass": {
        "AssetPathName": "None",
        "SubPathString": ""
      },
      "TargetName": "RewardDisplayPage",
      "MaskShape": 0,
      "MaskZoom": 0,
      "MaskType": 0,
      "DialogId": 0
    },
    "1000004": {
      "TaskSubid": 1000004,
      "TaskParentid": 10000,
      "TaskType": 2,
      "ParamType": 0,
      "TaskParam": 0,
      "PageClass": "NavigationPage",
      "ParentClass": {
        "AssetPathName": "None",
        "SubPathString": ""
      },
      "TargetName": "Button_Equip",
      "MaskShape": 0,
      "MaskZoom": 0,
      "MaskType": 1,
      "DialogId": 1000004
    },
    "1000005": {
      "TaskSubid": 1000005,
      "TaskParentid": 10000,
      "TaskType": 2,
      "ParamType": 3,
      "TaskParam": 105,
      "PageClass": "EquipRoomPage",
      "ParentClass": {
        "AssetPathName": "/Game/PaperMan/UI/BP/Mobile/Frontend/EquipRoom/New/WBP_RoleGridItemNew_Mobile.WBP_RoleGridItemNew_Mobile_C",
        "SubPathString": ""
      },
      "TargetName": "UPMBaseWidgetItem",
      "MaskShape": 0,
      "MaskZoom": 0,
      "MaskType": 1,
      "DialogId": 1000005
    },
    "1000006": {
      "TaskSubid": 1000006,
      "TaskParentid": 10000,
      "TaskType": 2,
      "ParamType": 0,
      "TaskParam": 0,
      "PageClass": "EquipRoomPage",
      "ParentClass": {
        "AssetPathName": "None",
        "SubPathString": ""
      },
      "TargetName": "Btn_RoleUnlock",
      "MaskShape": 0,
      "MaskZoom": 0,
      "MaskType": 1,
      "DialogId": 1000006
    },
    "1000007": {
      "TaskSubid": 1000007,
      "TaskParentid": 10000,
      "TaskType": 2,
      "ParamType": 4,
      "TaskParam": 2,
      "PageClass": "HermesPurchaseGoodsPage",
      "ParentClass": {
        "AssetPathName": "/Game/PaperMan/UI/BP/Mobile/Frontend/Hermes/HotList/WBP_HermesPurchaseGoodsPriceItem_Mobile.WBP_HermesPurchaseGoodsPriceItem_Mobile_C",
        "SubPathString": ""
      },
      "TargetName": "CurrencyButton",
      "MaskShape": 0,
      "MaskZoom": 0,
      "MaskType": 1,
      "DialogId": 1000007
    },
    "1000008": {
      "TaskSubid": 1000008,
      "TaskParentid": 10000,
      "TaskType": 2,
      "ParamType": 0,
      "TaskParam": 0,
      "PageClass": "HermesPurchaseGoodsPage",
      "ParentClass": {
        "AssetPathName": "None",
        "SubPathString": ""
      },
      "TargetName": "Button_Buy",
      "MaskShape": 0,
      "MaskZoom": 0,
      "MaskType": 1,
      "DialogId": 1000008
    },
    "1000101": {
      "TaskSubid": 1000101,
      "TaskParentid": 10001,
      "TaskType": 1,
      "ParamType": 0,
      "TaskParam": 0,
      "PageClass": "NavigationPage",
      "ParentClass": {
        "AssetPathName": "None",
        "SubPathString": ""
      },
      "TargetName": "",
      "MaskShape": 0,
      "MaskZoom": 0,
      "MaskType": 1,
      "DialogId": 1000101
    },
    "1000102": {
      "TaskSubid": 1000102,
      "TaskParentid": 10001,
      "TaskType": 1,
      "ParamType": 0,
      "TaskParam": 0,
      "PageClass": "NavigationPage",
      "ParentClass": {
        "AssetPathName": "None",
        "SubPathString": ""
      },
      "TargetName": "",
      "MaskShape": 0,
      "MaskZoom": 0,
      "MaskType": 1,
      "DialogId": 1000102
    },
    "1000103": {
      "TaskSubid": 1000103,
      "TaskParentid": 10001,
      "TaskType": 2,
      "ParamType": 0,
      "TaskParam": 0,
      "PageClass": "NavigationPage",
      "ParentClass": {
        "AssetPathName": "None",
        "SubPathString": ""
      },
      "TargetName": "Button_Play",
      "MaskShape": 0,
      "MaskZoom": 0,
      "MaskType": 1,
      "DialogId": 1000103
    },
    "1000104": {
      "TaskSubid": 1000104,
      "TaskParentid": 10001,
      "TaskType": 1,
      "ParamType": 0,
      "TaskParam": 0,
      "PageClass": "PlayModeSelectPage",
      "ParentClass": {
        "AssetPathName": "None",
        "SubPathString": ""
      },
      "TargetName": "",
      "MaskShape": 0,
      "MaskZoom": 0,
      "MaskType": 1,
      "DialogId": 1000104
    },
    "1000105": {
      "TaskSubid": 1000105,
      "TaskParentid": 10001,
      "TaskType": 2,
      "ParamType": 5,
      "TaskParam": 9,
      "PageClass": "PlayModeSelectPage",
      "ParentClass": {
        "AssetPathName": "/Game/PaperMan/UI/BP/Mobile/Frontend/Room/RoomMode/WBP_PlayModeSelectCard_Mobile.WBP_PlayModeSelectCard_Mobile_C",
        "SubPathString": ""
      },
      "TargetName": "Button_ModeCard",
      "MaskShape": 0,
      "MaskZoom": 0,
      "MaskType": 1,
      "DialogId": 1000105
    },
    "1000106": {
      "TaskSubid": 1000106,
      "TaskParentid": 10001,
      "TaskType": 4,
      "ParamType": 0,
      "TaskParam": 0,
      "PageClass": "PlayModeSelectPage",
      "ParentClass": {
        "AssetPathName": "None",
        "SubPathString": ""
      },
      "TargetName": "GuideGraphInstructionPage",
      "MaskShape": 0,
      "MaskZoom": 0,
      "MaskType": 0,
      "DialogId": 0
    },
    "1000107": {
      "TaskSubid": 1000107,
      "TaskParentid": 10001,
      "TaskType": 2,
      "ParamType": 0,
      "TaskParam": 0,
      "PageClass": "PlayModeSelectPage",
      "ParentClass": {
        "AssetPathName": "None",
        "SubPathString": ""
      },
      "TargetName": "Button_Confirm",
      "MaskShape": 0,
      "MaskZoom": 0,
      "MaskType": 1,
      "DialogId": 1000107
    },
    "1000108": {
      "TaskSubid": 1000108,
      "TaskParentid": 10001,
      "TaskType": 2,
      "ParamType": 0,
      "TaskParam": 0,
      "PageClass": "RankPCPage",
      "ParentClass": {
        "AssetPathName": "None",
        "SubPathString": ""
      },
      "TargetName": "Button_Type1",
      "MaskShape": 0,
      "MaskZoom": 0,
      "MaskType": 1,
      "DialogId": 1000108
    },
    "1000200": {
      "TaskSubid": 1000200,
      "TaskParentid": 10002,
      "TaskType": 4,
      "ParamType": 0,
      "TaskParam": 0,
      "PageClass": "RankPCPage",
      "ParentClass": {
        "AssetPathName": "None",
        "SubPathString": ""
      },
      "TargetName": "FunctionUnLockPopPage",
      "MaskShape": 0,
      "MaskZoom": 0,
      "MaskType": 0,
      "DialogId": 0
    },
    "1000201": {
      "TaskSubid": 1000201,
      "TaskParentid": 10002,
      "TaskType": 1,
      "ParamType": 0,
      "TaskParam": 0,
      "PageClass": "RankPCPage",
      "ParentClass": {
        "AssetPathName": "None",
        "SubPathString": ""
      },
      "TargetName": "",
      "MaskShape": 0,
      "MaskZoom": 0,
      "MaskType": 1,
      "DialogId": 1000201
    },
    "1000202": {
      "TaskSubid": 1000202,
      "TaskParentid": 10002,
      "TaskType": 1,
      "ParamType": 0,
      "TaskParam": 0,
      "PageClass": "RankPCPage",
      "ParentClass": {
        "AssetPathName": "None",
        "SubPathString": ""
      },
      "TargetName": "",
      "MaskShape": 0,
      "MaskZoom": 0,
      "MaskType": 1,
      "DialogId": 1000202
    },
    "1000203": {
      "TaskSubid": 1000203,
      "TaskParentid": 10002,
      "TaskType": 3,
      "ParamType": 0,
      "TaskParam": 3,
      "PageClass": "RankPCPage",
      "ParentClass": {
        "AssetPathName": "None",
        "SubPathString": ""
      },
      "TargetName": "RewardDisplayPage",
      "MaskShape": 0,
      "MaskZoom": 0,
      "MaskType": 0,
      "DialogId": 0
    },
    "1000204": {
      "TaskSubid": 1000204,
      "TaskParentid": 10002,
      "TaskType": 1,
      "ParamType": 0,
      "TaskParam": 0,
      "PageClass": "RankPCPage",
      "ParentClass": {
        "AssetPathName": "None",
        "SubPathString": ""
      },
      "TargetName": "",
      "MaskShape": 0,
      "MaskZoom": 0,
      "MaskType": 1,
      "DialogId": 1000204
    },
    "1000205": {
      "TaskSubid": 1000205,
      "TaskParentid": 10002,
      "TaskType": 2,
      "ParamType": 0,
      "TaskParam": 0,
      "PageClass": "RankPCPage",
      "ParentClass": {
        "AssetPathName": "None",
        "SubPathString": ""
      },
      "TargetName": "Button_ToLobby",
      "MaskShape": 0,
      "MaskZoom": 0,
      "MaskType": 1,
      "DialogId": 1000205
    },
    "1000206": {
      "TaskSubid": 1000206,
      "TaskParentid": 10002,
      "TaskType": 2,
      "ParamType": 0,
      "TaskParam": 0,
      "PageClass": "NavigationPage",
      "ParentClass": {
        "AssetPathName": "None",
        "SubPathString": ""
      },
      "TargetName": "Button_HermesActivity",
      "MaskShape": 0,
      "MaskZoom": 0,
      "MaskType": 1,
      "DialogId": 1000206
    },
    "1000207": {
      "TaskSubid": 1000207,
      "TaskParentid": 10002,
      "TaskType": 2,
      "ParamType": 6,
      "TaskParam": 2001,
      "PageClass": "LotteryMainPage",
      "ParentClass": {
        "AssetPathName": "/Game/PaperMan/UI/BP/Mobile/Frontend/Lottery/WBP_LotteryEntryItem_Mobile.WBP_LotteryEntryItem_Mobile_C",
        "SubPathString": ""
      },
      "TargetName": "ButtonClick",
      "MaskShape": 0,
      "MaskZoom": 0,
      "MaskType": 1,
      "DialogId": 1000207
    },
    "1000208": {
      "TaskSubid": 1000208,
      "TaskParentid": 10002,
      "TaskType": 2,
      "ParamType": 0,
      "TaskParam": 0,
      "PageClass": "LotteryEntryPage",
      "ParentClass": {
        "AssetPathName": "None",
        "SubPathString": ""
      },
      "TargetName": "Button_Enter",
      "MaskShape": 0,
      "MaskZoom": 0,
      "MaskType": 1,
      "DialogId": 1000208
    }
  }
}