{
  "Type": "DataTable",
  "Name": "RoleLevelExp",
  "Class": "UScriptClass'DataTable'",
  "Properties": {
    "RowStruct": {
      "ObjectName": "ScriptStruct'CyRoleLevelExpTableRow'",
      "ObjectPath": "/Script/PMGame"
    }
  },
  "Rows": {
    "RoleLevelExp": {
      "MaxLevel": 10,
      "MapExp": 3800,
      "Lv1Exp": 0,
      "Lv2Exp": 180,
      "Lv3Exp": 380,
      "Lv4Exp": 630,
      "Lv5Exp": 980,
      "Lv6Exp": 1380,
      "Lv7Exp": 1800,
      "Lv8Exp": 2200,
      "Lv9Exp": 2600,
      "Lv10Exp": 3000
    }
  }
}