{
  "Type": "AkAudioEvent",
  "Name": "Char_Result_Reiichi_MVP",
  "Class": "UScriptClass'AkAudioEvent'",
  "Flags": "RF_Public | RF_Standalone | RF_Transactional | RF_WasLoaded | RF_LoadCompleted",
  "Properties": {
    "MinimumDuration": 1.3211337,
    "MaximumDuration": 1.3211337,
    "RequiredBank": {
      "ObjectName": "AkAudioBank'Char_Result_Reiichi'",
      "ObjectPath": "PM/Content/WwiseAssets/AkBank/Char_Result_Reiichi.0"
    }
  },
  "EventCookedData": {
    "EventLanguageMap": [
      {
        "Key": {
          "LanguageId": 0,
          "LanguageName": "SFX",
          "LanguageRequirement": "EWwiseLanguageRequirement::SFX"
        },
        "Value": {
          "EventId": -1796124007,
          "SoundBanks": [
            {
              "SoundBankId": 286688715,
              "SoundBankPathName": "Char_Result_Reiichi.bnk",
              "MemoryAlignment": 16,
              "bDeviceMemory": false,
              "bContainsMedia": true,
              "SoundBankType": "EWwiseSoundBankType::User",
              "DebugName": "Char_Result_Reiichi"
            }
          ],
          "Media": [],
          "ExternalSources": [],
          "SwitchContainerLeaves": [],
          "RequiredGroupValueSet": [],
          "DestroyOptions": "EWwiseEventDestroyOptions::StopEventOnDestroy",
          "DebugName": "Char_Result_Reiichi_MVP"
        }
      }
    ],
    "DebugName": "Char_Result_Reiichi_MVP",
    "EventId": -1796124007
  },
  "MaximumDuration": 1.3211337,
  "MinimumDuration": 1.3211337,
  "IsInfinite": false,
  "MaxAttenuationRadius": 0.0
}