{
  "Type": "AkAudioEvent",
  "Name": "Char_3DFlavia_XSkill_Butterfly_Loop_Red",
  "Class": "UScriptClass'AkAudioEvent'",
  "Flags": "RF_Public | RF_Standalone | RF_Transactional | RF_WasLoaded | RF_LoadCompleted",
  "Properties": {
    "RequiredBank": {
      "ObjectName": "AkAudioBank'Char_3DFlavia_XSkill_Red'",
      "ObjectPath": "PM/Content/WwiseAssets/AkBank/Char_3DFlavia_XSkill_Red.0"
    }
  },
  "EventCookedData": {
    "EventLanguageMap": [
      {
        "Key": {
          "LanguageId": 0,
          "LanguageName": "SFX",
          "LanguageRequirement": "EWwiseLanguageRequirement::SFX"
        },
        "Value": {
          "EventId": -1015599035,
          "SoundBanks": [
            {
              "SoundBankId": -1170824036,
              "SoundBankPathName": "Char_3DFlavia_XSkill_Red.bnk",
              "MemoryAlignment": 16,
              "bDeviceMemory": false,
              "bContainsMedia": true,
              "SoundBankType": "EWwiseSoundBankType::User",
              "DebugName": "Char_3DFlavia_XSkill_Red"
            }
          ],
          "Media": [
            {
              "MediaId": 797108681,
              "MediaPathName": "Media/SFX/Char_3DFlavia_XSkill_Red/797108681.wem",
              "PrefetchSize": 0,
              "MemoryAlignment": 16,
              "bDeviceMemory": false,
              "bStreaming": true,
              "DebugName": "character\\3DFlavia\\Char_3DFlavia_Red\\Char_3DFlavia_XSkill_Butterfly_Loop_Red.wav"
            }
          ],
          "ExternalSources": [],
          "SwitchContainerLeaves": [],
          "RequiredGroupValueSet": [],
          "DestroyOptions": "EWwiseEventDestroyOptions::StopEventOnDestroy",
          "DebugName": "Char_3DFlavia_XSkill_Butterfly_Loop_Red"
        }
      }
    ],
    "DebugName": "Char_3DFlavia_XSkill_Butterfly_Loop_Red",
    "EventId": -1015599035
  },
  "MaximumDuration": 0.0,
  "MinimumDuration": 0.0,
  "IsInfinite": true,
  "MaxAttenuationRadius": 3000.0
}