{
  "Type": "AkAudioEvent",
  "Name": "Char_Galatea_ESkill_Pre",
  "Class": "UScriptClass'AkAudioEvent'",
  "Flags": "RF_Public | RF_Standalone | RF_Transactional | RF_WasLoaded | RF_LoadCompleted",
  "Properties": {
    "MinimumDuration": 1.283152,
    "MaximumDuration": 1.283152,
    "RequiredBank": {
      "ObjectName": "AkAudioBank'Char_Galatea_ESkill'",
      "ObjectPath": "PM/Content/WwiseAssets/AkBank/Char_Galatea_ESkill.0"
    }
  },
  "EventCookedData": {
    "EventLanguageMap": [
      {
        "Key": {
          "LanguageId": 0,
          "LanguageName": "SFX",
          "LanguageRequirement": "EWwiseLanguageRequirement::SFX"
        },
        "Value": {
          "EventId": 345348786,
          "SoundBanks": [
            {
              "SoundBankId": 1979719128,
              "SoundBankPathName": "Char_Galatea_ESkill.bnk",
              "MemoryAlignment": 16,
              "bDeviceMemory": false,
              "bContainsMedia": true,
              "SoundBankType": "EWwiseSoundBankType::User",
              "DebugName": "Char_Galatea_ESkill"
            }
          ],
          "Media": [],
          "ExternalSources": [],
          "SwitchContainerLeaves": [],
          "RequiredGroupValueSet": [],
          "DestroyOptions": "EWwiseEventDestroyOptions::StopEventOnDestroy",
          "DebugName": "Char_Galatea_ESkill_Pre"
        }
      }
    ],
    "DebugName": "Char_Galatea_ESkill_Pre",
    "EventId": 345348786
  },
  "MaximumDuration": 1.283152,
  "MinimumDuration": 1.283152,
  "IsInfinite": false,
  "MaxAttenuationRadius": 3000.0
}