{
  "Type": "AkAudioEvent",
  "Name": "Vox_Audrey_Birthday_012",
  "Class": "UScriptClass'AkAudioEvent'",
  "Properties": {
    "RequiredBank": {
      "ObjectName": "AkAudioBank'Vox_Audrey_OutGame_Lounge_original'",
      "ObjectPath": "PM/Content/WwiseAssets/AkBank/Vox_Audrey_OutGame_Lounge_original.0"
    },
    "MultiLanguage": true,
    "MinimumDuration": 4.01263,
    "MaximumDuration": 4.01263,
    "MultiMinimumDuration": [
      4.01263,
      1.0,
      1.0
    ],
    "MultiMaximumDuration": [
      4.01263,
      1.0,
      1.0
    ],
    "bHavePrefetchSize": true,
    "ShortID": 2933411615
  }
}