{
  "Type": "AkAudioEvent",
  "Name": "Vox_HuiXing_BPCHAR_022",
  "Class": "UScriptClass'AkAudioEvent'",
  "Properties": {
    "MultiLanguage": true,
    "MinimumDuration": 1.7595011,
    "MaximumDuration": 1.7595011,
    "MultiMinimumDuration": [
      1.7595011,
      1.0,
      2.0698185
    ],
    "MultiMaximumDuration": [
      1.7595011,
      1.0,
      2.0698185
    ],
    "RequiredBank": {
      "ObjectName": "AkAudioBank'Vox_Logo'",
      "ObjectPath": "PM/Content/WwiseAssets/AkBank/Vox_Logo.0"
    }
  }
}