{
  "Type": "AkAudioEvent",
  "Name": "Vox_BP2_EP5_007",
  "Class": "UScriptClass'AkAudioEvent'",
  "Properties": {
    "MultiLanguage": true,
    "MinimumDuration": 0.8205669,
    "MaximumDuration": 0.8205669,
    "MultiMinimumDuration": [
      0.8205669,
      0.8205669
    ],
    "MultiMaximumDuration": [
      0.8205669,
      0.8205669
    ],
    "RequiredBank": {
      "ObjectName": "AkAudioBank'Vox_Story_BP2_EP5_02'",
      "ObjectPath": "PM/Content/WwiseAssets/AkBank/Vox_Story_BP2_EP5_02.0"
    }
  }
}