{
  "Type": "AkAudioEvent",
  "Name": "Vox_Audrey_BPCHAT_077",
  "Class": "UScriptClass'AkAudioEvent'",
  "Properties": {
    "MultiLanguage": true,
    "MinimumDuration": 2.0451927,
    "MaximumDuration": 3.0451927,
    "MultiMinimumDuration": [
      2.0451927,
      1.4727892
    ],
    "MultiMaximumDuration": [
      3.0451927,
      2.4728117
    ],
    "RequiredBank": {
      "ObjectName": "AkAudioBank'Vox_Audrey_InGame_Kill_original'",
      "ObjectPath": "PM/Content/WwiseAssets/AkBank/Vox_Audrey_InGame_Kill_original.0"
    }
  }
}