{
  "Type": "AkAudioEvent",
  "Name": "Vox_Michele_163",
  "Class": "UScriptClass'AkAudioEvent'",
  "Properties": {
    "RequiredBank": {
      "ObjectName": "AkAudioBank'Vox_Michele_OutGame_Lounge_original'",
      "ObjectPath": "PM/Content/WwiseAssets/AkBank/Vox_Michele_OutGame_Lounge_original.0"
    },
    "MultiLanguage": true,
    "MinimumDuration": 16.155783,
    "MaximumDuration": 16.155783,
    "MultiMinimumDuration": [
      16.155783,
      22.56177,
      15.52746
    ],
    "MultiMaximumDuration": [
      16.155783,
      22.56177,
      15.52746
    ],
    "bHavePrefetchSize": true,
    "ShortID": 2590597165
  }
}