{
  "Type": "AkAudioEvent",
  "Name": "Vox_MoBai_COM_087",
  "Class": "UScriptClass'AkAudioEvent'",
  "Properties": {
    "RequiredBank": {
      "ObjectName": "AkAudioBank'Vox_MoBai_InGame_Shortcut_original'",
      "ObjectPath": "PM/Content/WwiseAssets/AkBank/Vox_MoBai_InGame_Shortcut_original.0"
    },
    "MaxAttenuationRadius": 15000.0,
    "MultiLanguage": true,
    "MinimumDuration": 0.523414,
    "MaximumDuration": 0.523414,
    "MultiMinimumDuration": [
      0.523414,
      1.036092,
      0.674961
    ],
    "MultiMaximumDuration": [
      0.523414,
      1.036092,
      0.674961
    ],
    "ShortID": 1972714725
  }
}