{
  "Type": "AkAudioEvent",
  "Name": "Vox_Mara_BPCHAT_076",
  "Class": "UScriptClass'AkAudioEvent'",
  "Properties": {
    "MultiLanguage": true,
    "MinimumDuration": 3.2586622,
    "MaximumDuration": 3.2586622,
    "MultiMinimumDuration": [
      3.2586622,
      2.4665306
    ],
    "MultiMaximumDuration": [
      3.2586622,
      2.4665306
    ],
    "RequiredBank": {
      "ObjectName": "AkAudioBank'Vox_Mara_InGame_Skill_original'",
      "ObjectPath": "PM/Content/WwiseAssets/AkBank/Vox_Mara_InGame_Skill_original.0"
    }
  }
}