{
  "Type": "AkAudioEvent",
  "Name": "Vox_Reiichi_BPCHAR_020_VoList",
  "Class": "UScriptClass'AkAudioEvent'",
  "Properties": {
    "MultiLanguage": true,
    "MinimumDuration": 0.46666667,
    "MaximumDuration": 0.46666667,
    "MultiMinimumDuration": [
      0.46666667,
      0.7109524,
      1.3624717
    ],
    "MultiMaximumDuration": [
      0.46666667,
      0.7109524,
      1.3624717
    ],
    "RequiredBank": {
      "ObjectName": "AkAudioBank'Vox_Reiichi_OutGame_VoList_original'",
      "ObjectPath": "PM/Content/WwiseAssets/AkBank/Vox_Reiichi_OutGame_VoList_original.0"
    }
  }
}