{
  "Type": "AkAudioEvent",
  "Name": "Vox_HuiXing_BPCHAR_040_a",
  "Class": "UScriptClass'AkAudioEvent'",
  "Properties": {
    "RequiredBank": {
      "ObjectName": "AkAudioBank'Vox_HuiXing_OutGame_Lounge_original'",
      "ObjectPath": "PM/Content/WwiseAssets/AkBank/Vox_HuiXing_OutGame_Lounge_original.0"
    },
    "MultiLanguage": true,
    "MinimumDuration": 20.725964,
    "MaximumDuration": 20.725964,
    "MultiMinimumDuration": [
      20.725964,
      15.952744,
      13.072585
    ],
    "MultiMaximumDuration": [
      20.725964,
      15.952744,
      13.072585
    ],
    "ShortID": 2383650045
  }
}