{
  "Type": "AkAudioEvent",
  "Name": "Vox_Leona_502",
  "Class": "UScriptClass'AkAudioEvent'",
  "Properties": {
    "MultiLanguage": true,
    "MinimumDuration": 0.7464172,
    "MaximumDuration": 0.7464172,
    "MultiMinimumDuration": [
      0.7464172,
      1.2591836,
      1.1176871
    ],
    "MultiMaximumDuration": [
      0.7464172,
      1.2591836,
      1.1176871
    ],
    "RequiredBank": {
      "ObjectName": "AkAudioBank'Vox_Leona_InGame_Barrier_free_original'",
      "ObjectPath": "PM/Content/WwiseAssets/AkBank/Vox_Leona_InGame_Barrier_free_original.0"
    }
  }
}