{
  "Type": "AkAudioEvent",
  "Name": "Vox_BP2_EP7_037",
  "Class": "UScriptClass'AkAudioEvent'",
  "Properties": {
    "MultiLanguage": true,
    "MinimumDuration": 1.8763492,
    "MaximumDuration": 1.8763492,
    "MultiMinimumDuration": [
      1.8763492,
      1.8763492
    ],
    "MultiMaximumDuration": [
      1.8763492,
      1.8763492
    ],
    "RequiredBank": {
      "ObjectName": "AkAudioBank'Vox_Story_BP2_EP7_08'",
      "ObjectPath": "PM/Content/WwiseAssets/AkBank/Vox_Story_BP2_EP7_08.0"
    }
  }
}