{
  "Type": "AkAudioEvent",
  "Name": "Vox_Michele_COM_097",
  "Class": "UScriptClass'AkAudioEvent'",
  "Properties": {
    "RequiredBank": {
      "ObjectName": "AkAudioBank'Vox_Michele_InGame_Tactical_Item_original'",
      "ObjectPath": "PM/Content/WwiseAssets/AkBank/Vox_Michele_InGame_Tactical_Item_original.0"
    },
    "MaxAttenuationRadius": 15000.0,
    "MultiLanguage": true,
    "MinimumDuration": 3.382449,
    "MaximumDuration": 3.382449,
    "MultiMinimumDuration": [
      3.382449,
      2.716281,
      1.265873
    ],
    "MultiMaximumDuration": [
      3.382449,
      2.716281,
      1.265873
    ],
    "ShortID": 406018391
  }
}