{
  "Type": "AkAudioEvent",
  "Name": "Vox_BP3_EP1_101",
  "Class": "UScriptClass'AkAudioEvent'",
  "Properties": {
    "MultiLanguage": true,
    "MinimumDuration": 6.3726077,
    "MaximumDuration": 6.3726077,
    "MultiMinimumDuration": [
      6.3726077,
      6.3726077,
      6.3726077
    ],
    "MultiMaximumDuration": [
      6.3726077,
      6.3726077,
      6.3726077
    ],
    "RequiredBank": {
      "ObjectName": "AkAudioBank'Vox_Story_BP3_EP1_21'",
      "ObjectPath": "PM/Content/WwiseAssets/AkBank/Vox_Story_BP3_EP1_21.0"
    }
  }
}