{
  "Type": "AkAudioEvent",
  "Name": "Vox_Michele_BPCHAT_080",
  "Class": "UScriptClass'AkAudioEvent'",
  "Properties": {
    "MultiLanguage": true,
    "MinimumDuration": 3.3752382,
    "MaximumDuration": 3.3752382,
    "MultiMinimumDuration": [
      3.3752382,
      2.3014286,
      1.9022223
    ],
    "MultiMaximumDuration": [
      3.3752382,
      2.3014286,
      1.9022223
    ],
    "RequiredBank": {
      "ObjectName": "AkAudioBank'Vox_Michele_InGame_Skill_original'",
      "ObjectPath": "PM/Content/WwiseAssets/AkBank/Vox_Michele_InGame_Skill_original.0"
    }
  }
}